LICENSE
README.md
setup.py
wandc/__init__.py
wandc/emissions_logger.py
wandc/logger.py
wandc.egg-info/PKG-INFO
wandc.egg-info/SOURCES.txt
wandc.egg-info/dependency_links.txt
wandc.egg-info/requires.txt
wandc.egg-info/top_level.txt