Metadata-Version: 2.1
Name: wandc
Version: 0.0.2
Summary: A wandb and codecarbon wrapper that logs water and carbon consumption for your experiments on cloud.
Home-page: https://github.com/ielab/wandc
Author: Shengyao Zhuang
Author-email: s.zhuang@uq.edu.au
License: Apache 2.0
Requires-Python: >=3.8
License-File: LICENSE
